{
  "meta": {
    "textbook": "История России, 6 класс, В. Р. Мединский",
    "section": "§ 26—27 Русские земли и Золотая Орда",
    "note": "Банк вопросов для 6 класса. У каждого вопроса указан источник: страница и параграф."
  },
  "questions": [
    {
      "id": "g6-rus-s26-27-001",
      "type": "single_choice",
      "question": "Какое утверждение верно характеризует понятие или событие «Золотая Орда»?",
      "options": [
        "дань, которую русские земли платили Орде",
        "государство, возникшее в западной части монгольских владений и подчинившее русские земли",
        "система политического и финансового подчинения русских земель ханам",
        "ханская грамота, дававшая право на княжение"
      ],
      "correct_answers": [
        "государство, возникшее в западной части монгольских владений и подчинившее русские земли"
      ],
      "explanation": "В теме «Русские земли и Золотая Орда» понятие или событие «Золотая Орда» означает: государство, возникшее в западной части монгольских владений и подчинившее русские земли.",
      "source": {
        "paragraph": "§26-27",
        "page": 135
      },
      "difficulty": {
        "primary": "easy",
        "secondary": "easy"
      },
      "tags": {
        "entities": [],
        "concepts": [
          "Русские земли и Золотая Орда",
          "Золотая Орда"
        ],
        "processes": [],
        "periods": [
          "XIII—XIV вв."
        ],
        "skills": [
          "knowledge"
        ],
        "geography": [
          "Золотая Орда",
          "Сарай",
          "Русские земли"
        ],
        "difficulty": "easy",
        "question_type": "single_choice",
        "grade": [
          6
        ],
        "source": "Мединский, История России, 6 кл.",
        "themes": [
          "Русские земли и Золотая Орда"
        ]
      }
    },
    {
      "id": "g6-rus-s26-27-002",
      "type": "single_choice",
      "question": "Какое утверждение верно характеризует понятие или событие «Сарай»?",
      "options": [
        "явление более поздней эпохи Нового времени",
        "дань, которую русские земли платили Орде",
        "ханские представители, контролировавшие сбор дани на раннем этапе зависимости",
        "столица Золотой Орды"
      ],
      "correct_answers": [
        "столица Золотой Орды"
      ],
      "explanation": "В теме «Русские земли и Золотая Орда» понятие или событие «Сарай» означает: столица Золотой Орды.",
      "source": {
        "paragraph": "§26-27",
        "page": 135
      },
      "difficulty": {
        "primary": "easy",
        "secondary": "easy"
      },
      "tags": {
        "entities": [],
        "concepts": [
          "Русские земли и Золотая Орда",
          "Сарай"
        ],
        "processes": [],
        "periods": [
          "XIII—XIV вв."
        ],
        "skills": [
          "knowledge"
        ],
        "geography": [
          "Золотая Орда",
          "Сарай",
          "Русские земли"
        ],
        "difficulty": "easy",
        "question_type": "single_choice",
        "grade": [
          6
        ],
        "source": "Мединский, История России, 6 кл.",
        "themes": [
          "Русские земли и Золотая Орда"
        ]
      }
    },
    {
      "id": "g6-rus-s26-27-003",
      "type": "single_choice",
      "question": "Какое утверждение верно характеризует понятие или событие «Хан»?",
      "options": [
        "мера Орды для учёта плательщиков дани",
        "столица Золотой Орды",
        "событие, не относящееся к истории Руси IX — первой трети XVI в.",
        "правитель Орды, от которого зависело утверждение русских князей"
      ],
      "correct_answers": [
        "правитель Орды, от которого зависело утверждение русских князей"
      ],
      "explanation": "В теме «Русские земли и Золотая Орда» понятие или событие «Хан» означает: правитель Орды, от которого зависело утверждение русских князей.",
      "source": {
        "paragraph": "§26-27",
        "page": 135
      },
      "difficulty": {
        "primary": "easy",
        "secondary": "easy"
      },
      "tags": {
        "entities": [],
        "concepts": [
          "Русские земли и Золотая Орда",
          "Хан"
        ],
        "processes": [],
        "periods": [
          "XIII—XIV вв."
        ],
        "skills": [
          "knowledge"
        ],
        "geography": [
          "Золотая Орда",
          "Сарай",
          "Русские земли"
        ],
        "difficulty": "easy",
        "question_type": "single_choice",
        "grade": [
          6
        ],
        "source": "Мединский, История России, 6 кл.",
        "themes": [
          "Русские земли и Золотая Орда"
        ]
      }
    },
    {
      "id": "g6-rus-s26-27-004",
      "type": "single_choice",
      "question": "Какое утверждение верно характеризует понятие или событие «Ярлык»?",
      "options": [
        "ханская грамота, дававшая право на княжение",
        "событие, не относящееся к истории Руси IX — первой трети XVI в.",
        "разорение, выплаты дани, политическая зависимость и сохранение раздробленности",
        "система политического и финансового подчинения русских земель ханам"
      ],
      "correct_answers": [
        "ханская грамота, дававшая право на княжение"
      ],
      "explanation": "В теме «Русские земли и Золотая Орда» понятие или событие «Ярлык» означает: ханская грамота, дававшая право на княжение.",
      "source": {
        "paragraph": "§26-27",
        "page": 135
      },
      "difficulty": {
        "primary": "easy",
        "secondary": "easy"
      },
      "tags": {
        "entities": [],
        "concepts": [
          "Русские земли и Золотая Орда",
          "Ярлык"
        ],
        "processes": [],
        "periods": [
          "XIII—XIV вв."
        ],
        "skills": [
          "knowledge"
        ],
        "geography": [
          "Золотая Орда",
          "Сарай",
          "Русские земли"
        ],
        "difficulty": "easy",
        "question_type": "single_choice",
        "grade": [
          6
        ],
        "source": "Мединский, История России, 6 кл.",
        "themes": [
          "Русские земли и Золотая Орда"
        ]
      }
    },
    {
      "id": "g6-rus-s26-27-005",
      "type": "single_choice",
      "question": "Какое утверждение верно характеризует понятие или событие «Выход»?",
      "options": [
        "необходимая часть получения ярлыков и подтверждения власти",
        "объяснение, относящееся к другой теме курса",
        "сохранила важное положение и способствовала духовному единству Руси",
        "дань, которую русские земли платили Орде"
      ],
      "correct_answers": [
        "дань, которую русские земли платили Орде"
      ],
      "explanation": "В теме «Русские земли и Золотая Орда» понятие или событие «Выход» означает: дань, которую русские земли платили Орде.",
      "source": {
        "paragraph": "§26-27",
        "page": 135
      },
      "difficulty": {
        "primary": "easy",
        "secondary": "easy"
      },
      "tags": {
        "entities": [],
        "concepts": [
          "Русские земли и Золотая Орда",
          "Выход"
        ],
        "processes": [],
        "periods": [
          "XIII—XIV вв."
        ],
        "skills": [
          "knowledge"
        ],
        "geography": [
          "Золотая Орда",
          "Сарай",
          "Русские земли"
        ],
        "difficulty": "easy",
        "question_type": "single_choice",
        "grade": [
          6
        ],
        "source": "Мединский, История России, 6 кл.",
        "themes": [
          "Русские земли и Золотая Орда"
        ]
      }
    },
    {
      "id": "g6-rus-s26-27-006",
      "type": "single_choice",
      "question": "Какое утверждение верно характеризует понятие или событие «Баскаки»?",
      "options": [
        "правитель Орды, от которого зависело утверждение русских князей",
        "ханские представители, контролировавшие сбор дани на раннем этапе зависимости",
        "система политического и финансового подчинения русских земель ханам",
        "необходимая часть получения ярлыков и подтверждения власти"
      ],
      "correct_answers": [
        "ханские представители, контролировавшие сбор дани на раннем этапе зависимости"
      ],
      "explanation": "В теме «Русские земли и Золотая Орда» понятие или событие «Баскаки» означает: ханские представители, контролировавшие сбор дани на раннем этапе зависимости.",
      "source": {
        "paragraph": "§26-27",
        "page": 135
      },
      "difficulty": {
        "primary": "easy",
        "secondary": "easy"
      },
      "tags": {
        "entities": [],
        "concepts": [
          "Русские земли и Золотая Орда",
          "Баскаки"
        ],
        "processes": [],
        "periods": [
          "XIII—XIV вв."
        ],
        "skills": [
          "knowledge"
        ],
        "geography": [
          "Золотая Орда",
          "Сарай",
          "Русские земли"
        ],
        "difficulty": "easy",
        "question_type": "single_choice",
        "grade": [
          6
        ],
        "source": "Мединский, История России, 6 кл.",
        "themes": [
          "Русские земли и Золотая Орда"
        ]
      }
    },
    {
      "id": "g6-rus-s26-27-007",
      "type": "single_choice",
      "question": "Какое утверждение верно характеризует понятие или событие «Ордынская зависимость»?",
      "options": [
        "система политического и финансового подчинения русских земель ханам",
        "термин из истории Древнего мира, не раскрывающий тему",
        "государство, возникшее в западной части монгольских владений и подчинившее русские земли",
        "мера Орды для учёта плательщиков дани"
      ],
      "correct_answers": [
        "система политического и финансового подчинения русских земель ханам"
      ],
      "explanation": "В теме «Русские земли и Золотая Орда» понятие или событие «Ордынская зависимость» означает: система политического и финансового подчинения русских земель ханам.",
      "source": {
        "paragraph": "§26-27",
        "page": 135
      },
      "difficulty": {
        "primary": "medium",
        "secondary": "medium"
      },
      "tags": {
        "entities": [],
        "concepts": [
          "Русские земли и Золотая Орда",
          "Ордынская зависимость"
        ],
        "processes": [],
        "periods": [
          "XIII—XIV вв."
        ],
        "skills": [
          "knowledge"
        ],
        "geography": [
          "Золотая Орда",
          "Сарай",
          "Русские земли"
        ],
        "difficulty": "medium",
        "question_type": "single_choice",
        "grade": [
          6
        ],
        "source": "Мединский, История России, 6 кл.",
        "themes": [
          "Русские земли и Золотая Орда"
        ]
      }
    },
    {
      "id": "g6-rus-s26-27-008",
      "type": "single_choice",
      "question": "Какое утверждение верно характеризует понятие или событие «Перепись населения»?",
      "options": [
        "столица Золотой Орды",
        "сохранила важное положение и способствовала духовному единству Руси",
        "мера Орды для учёта плательщиков дани",
        "ханская грамота, дававшая право на княжение"
      ],
      "correct_answers": [
        "мера Орды для учёта плательщиков дани"
      ],
      "explanation": "В теме «Русские земли и Золотая Орда» понятие или событие «Перепись населения» означает: мера Орды для учёта плательщиков дани.",
      "source": {
        "paragraph": "§26-27",
        "page": 135
      },
      "difficulty": {
        "primary": "medium",
        "secondary": "medium"
      },
      "tags": {
        "entities": [],
        "concepts": [
          "Русские земли и Золотая Орда",
          "Перепись населения"
        ],
        "processes": [],
        "periods": [
          "XIII—XIV вв."
        ],
        "skills": [
          "knowledge"
        ],
        "geography": [
          "Золотая Орда",
          "Сарай",
          "Русские земли"
        ],
        "difficulty": "medium",
        "question_type": "single_choice",
        "grade": [
          6
        ],
        "source": "Мединский, История России, 6 кл.",
        "themes": [
          "Русские земли и Золотая Орда"
        ]
      }
    },
    {
      "id": "g6-rus-s26-27-009",
      "type": "single_choice",
      "question": "Какое утверждение верно характеризует понятие или событие «Княжеские поездки в Орду»?",
      "options": [
        "необходимая часть получения ярлыков и подтверждения власти",
        "система политического и финансового подчинения русских земель ханам",
        "мера Орды для учёта плательщиков дани",
        "дань, которую русские земли платили Орде"
      ],
      "correct_answers": [
        "необходимая часть получения ярлыков и подтверждения власти"
      ],
      "explanation": "В теме «Русские земли и Золотая Орда» понятие или событие «Княжеские поездки в Орду» означает: необходимая часть получения ярлыков и подтверждения власти.",
      "source": {
        "paragraph": "§26-27",
        "page": 135
      },
      "difficulty": {
        "primary": "medium",
        "secondary": "medium"
      },
      "tags": {
        "entities": [],
        "concepts": [
          "Русские земли и Золотая Орда",
          "Княжеские поездки в Орду"
        ],
        "processes": [],
        "periods": [
          "XIII—XIV вв."
        ],
        "skills": [
          "knowledge"
        ],
        "geography": [
          "Золотая Орда",
          "Сарай",
          "Русские земли"
        ],
        "difficulty": "medium",
        "question_type": "single_choice",
        "grade": [
          6
        ],
        "source": "Мединский, История России, 6 кл.",
        "themes": [
          "Русские земли и Золотая Орда"
        ]
      }
    },
    {
      "id": "g6-rus-s26-27-010",
      "type": "single_choice",
      "question": "Какое утверждение верно характеризует понятие или событие «Православная церковь»?",
      "options": [
        "сохранила важное положение и способствовала духовному единству Руси",
        "необходимая часть получения ярлыков и подтверждения власти",
        "событие, не относящееся к истории Руси IX — первой трети XVI в.",
        "правитель Орды, от которого зависело утверждение русских князей"
      ],
      "correct_answers": [
        "сохранила важное положение и способствовала духовному единству Руси"
      ],
      "explanation": "В теме «Русские земли и Золотая Орда» понятие или событие «Православная церковь» означает: сохранила важное положение и способствовала духовному единству Руси.",
      "source": {
        "paragraph": "§26-27",
        "page": 135
      },
      "difficulty": {
        "primary": "medium",
        "secondary": "medium"
      },
      "tags": {
        "entities": [],
        "concepts": [
          "Русские земли и Золотая Орда",
          "Православная церковь"
        ],
        "processes": [],
        "periods": [
          "XIII—XIV вв."
        ],
        "skills": [
          "knowledge"
        ],
        "geography": [
          "Золотая Орда",
          "Сарай",
          "Русские земли"
        ],
        "difficulty": "medium",
        "question_type": "single_choice",
        "grade": [
          6
        ],
        "source": "Мединский, История России, 6 кл.",
        "themes": [
          "Русские земли и Золотая Орда"
        ]
      }
    },
    {
      "id": "g6-rus-s26-27-011",
      "type": "single_choice",
      "question": "Какое утверждение верно характеризует понятие или событие «Последствия зависимости»?",
      "options": [
        "разорение, выплаты дани, политическая зависимость и сохранение раздробленности",
        "ханские представители, контролировавшие сбор дани на раннем этапе зависимости",
        "термин из истории Древнего мира, не раскрывающий тему",
        "мера Орды для учёта плательщиков дани"
      ],
      "correct_answers": [
        "разорение, выплаты дани, политическая зависимость и сохранение раздробленности"
      ],
      "explanation": "В теме «Русские земли и Золотая Орда» понятие или событие «Последствия зависимости» означает: разорение, выплаты дани, политическая зависимость и сохранение раздробленности.",
      "source": {
        "paragraph": "§26-27",
        "page": 135
      },
      "difficulty": {
        "primary": "medium",
        "secondary": "medium"
      },
      "tags": {
        "entities": [],
        "concepts": [
          "Русские земли и Золотая Орда",
          "Последствия зависимости"
        ],
        "processes": [],
        "periods": [
          "XIII—XIV вв."
        ],
        "skills": [
          "knowledge"
        ],
        "geography": [
          "Золотая Орда",
          "Сарай",
          "Русские земли"
        ],
        "difficulty": "medium",
        "question_type": "single_choice",
        "grade": [
          6
        ],
        "source": "Мединский, История России, 6 кл.",
        "themes": [
          "Русские земли и Золотая Орда"
        ]
      }
    },
    {
      "id": "g6-rus-s26-27-012",
      "type": "single_choice",
      "question": "Какое утверждение верно характеризует понятие или событие «Приспособление князей»?",
      "options": [
        "политика, позволявшая сохранить земли и постепенно накопить силы",
        "необходимая часть получения ярлыков и подтверждения власти",
        "правитель Орды, от которого зависело утверждение русских князей",
        "объяснение, относящееся к другой теме курса"
      ],
      "correct_answers": [
        "политика, позволявшая сохранить земли и постепенно накопить силы"
      ],
      "explanation": "В теме «Русские земли и Золотая Орда» понятие или событие «Приспособление князей» означает: политика, позволявшая сохранить земли и постепенно накопить силы.",
      "source": {
        "paragraph": "§26-27",
        "page": 135
      },
      "difficulty": {
        "primary": "medium",
        "secondary": "medium"
      },
      "tags": {
        "entities": [],
        "concepts": [
          "Русские земли и Золотая Орда",
          "Приспособление князей"
        ],
        "processes": [],
        "periods": [
          "XIII—XIV вв."
        ],
        "skills": [
          "knowledge"
        ],
        "geography": [
          "Золотая Орда",
          "Сарай",
          "Русские земли"
        ],
        "difficulty": "medium",
        "question_type": "single_choice",
        "grade": [
          6
        ],
        "source": "Мединский, История России, 6 кл.",
        "themes": [
          "Русские земли и Золотая Орда"
        ]
      }
    },
    {
      "id": "g6-rus-s26-27-013",
      "type": "single_choice",
      "question": "Что относится к понятию или событию «Выход» в теме «Русские земли и Золотая Орда»?",
      "options": [
        "дань, которую русские земли платили Орде",
        "необходимая часть получения ярлыков и подтверждения власти",
        "мера Орды для учёта плательщиков дани",
        "ханская грамота, дававшая право на княжение"
      ],
      "correct_answers": [
        "дань, которую русские земли платили Орде"
      ],
      "explanation": "В теме «Русские земли и Золотая Орда» понятие или событие «Выход» означает: дань, которую русские земли платили Орде.",
      "source": {
        "paragraph": "§26-27",
        "page": 135
      },
      "difficulty": {
        "primary": "medium",
        "secondary": "medium"
      },
      "tags": {
        "entities": [],
        "concepts": [
          "Русские земли и Золотая Орда",
          "Выход"
        ],
        "processes": [],
        "periods": [
          "XIII—XIV вв."
        ],
        "skills": [
          "knowledge"
        ],
        "geography": [
          "Золотая Орда",
          "Сарай",
          "Русские земли"
        ],
        "difficulty": "medium",
        "question_type": "single_choice",
        "grade": [
          6
        ],
        "source": "Мединский, История России, 6 кл.",
        "themes": [
          "Русские земли и Золотая Орда"
        ]
      }
    },
    {
      "id": "g6-rus-s26-27-014",
      "type": "single_choice",
      "question": "Что относится к понятию или событию «Баскаки» в теме «Русские земли и Золотая Орда»?",
      "options": [
        "явление более поздней эпохи Нового времени",
        "политика, позволявшая сохранить земли и постепенно накопить силы",
        "столица Золотой Орды",
        "ханские представители, контролировавшие сбор дани на раннем этапе зависимости"
      ],
      "correct_answers": [
        "ханские представители, контролировавшие сбор дани на раннем этапе зависимости"
      ],
      "explanation": "В теме «Русские земли и Золотая Орда» понятие или событие «Баскаки» означает: ханские представители, контролировавшие сбор дани на раннем этапе зависимости.",
      "source": {
        "paragraph": "§26-27",
        "page": 135
      },
      "difficulty": {
        "primary": "medium",
        "secondary": "medium"
      },
      "tags": {
        "entities": [],
        "concepts": [
          "Русские земли и Золотая Орда",
          "Баскаки"
        ],
        "processes": [],
        "periods": [
          "XIII—XIV вв."
        ],
        "skills": [
          "knowledge"
        ],
        "geography": [
          "Золотая Орда",
          "Сарай",
          "Русские земли"
        ],
        "difficulty": "medium",
        "question_type": "single_choice",
        "grade": [
          6
        ],
        "source": "Мединский, История России, 6 кл.",
        "themes": [
          "Русские земли и Золотая Орда"
        ]
      }
    },
    {
      "id": "g6-rus-s26-27-015",
      "type": "single_choice",
      "question": "Что относится к понятию или событию «Ордынская зависимость» в теме «Русские земли и Золотая Орда»?",
      "options": [
        "сохранила важное положение и способствовала духовному единству Руси",
        "термин из истории Древнего мира, не раскрывающий тему",
        "правитель Орды, от которого зависело утверждение русских князей",
        "система политического и финансового подчинения русских земель ханам"
      ],
      "correct_answers": [
        "система политического и финансового подчинения русских земель ханам"
      ],
      "explanation": "В теме «Русские земли и Золотая Орда» понятие или событие «Ордынская зависимость» означает: система политического и финансового подчинения русских земель ханам.",
      "source": {
        "paragraph": "§26-27",
        "page": 135
      },
      "difficulty": {
        "primary": "medium",
        "secondary": "medium"
      },
      "tags": {
        "entities": [],
        "concepts": [
          "Русские земли и Золотая Орда",
          "Ордынская зависимость"
        ],
        "processes": [],
        "periods": [
          "XIII—XIV вв."
        ],
        "skills": [
          "knowledge"
        ],
        "geography": [
          "Золотая Орда",
          "Сарай",
          "Русские земли"
        ],
        "difficulty": "medium",
        "question_type": "single_choice",
        "grade": [
          6
        ],
        "source": "Мединский, История России, 6 кл.",
        "themes": [
          "Русские земли и Золотая Орда"
        ]
      }
    },
    {
      "id": "g6-rus-s26-27-016",
      "type": "open",
      "question": "Кратко объясните значение понятия или события «Перепись населения».",
      "correct_answer": "мера Орды для учёта плательщиков дани",
      "acceptable_answers": [
        "мера Орды для учёта плательщиков дани",
        "Перепись населения: мера Орды для учёта плательщиков дани"
      ],
      "explanation": "Ответ должен раскрывать смысл термина в теме «Русские земли и Золотая Орда»: мера Орды для учёта плательщиков дани.",
      "source": {
        "paragraph": "§26-27",
        "page": 135
      },
      "difficulty": {
        "primary": "hard",
        "secondary": "medium"
      },
      "tags": {
        "entities": [],
        "concepts": [
          "Русские земли и Золотая Орда",
          "Перепись населения"
        ],
        "processes": [],
        "periods": [
          "XIII—XIV вв."
        ],
        "skills": [
          "explanation"
        ],
        "geography": [
          "Золотая Орда",
          "Сарай",
          "Русские земли"
        ],
        "difficulty": "hard",
        "question_type": "open",
        "grade": [
          6
        ],
        "source": "Мединский, История России, 6 кл.",
        "themes": [
          "Русские земли и Золотая Орда"
        ]
      }
    },
    {
      "id": "g6-rus-s26-27-017",
      "type": "open",
      "question": "Кратко объясните значение понятия или события «Княжеские поездки в Орду».",
      "correct_answer": "необходимая часть получения ярлыков и подтверждения власти",
      "acceptable_answers": [
        "необходимая часть получения ярлыков и подтверждения власти",
        "Княжеские поездки в Орду: необходимая часть получения ярлыков и подтверждения власти"
      ],
      "explanation": "Ответ должен раскрывать смысл термина в теме «Русские земли и Золотая Орда»: необходимая часть получения ярлыков и подтверждения власти.",
      "source": {
        "paragraph": "§26-27",
        "page": 135
      },
      "difficulty": {
        "primary": "hard",
        "secondary": "medium"
      },
      "tags": {
        "entities": [],
        "concepts": [
          "Русские земли и Золотая Орда",
          "Княжеские поездки в Орду"
        ],
        "processes": [],
        "periods": [
          "XIII—XIV вв."
        ],
        "skills": [
          "explanation"
        ],
        "geography": [
          "Золотая Орда",
          "Сарай",
          "Русские земли"
        ],
        "difficulty": "hard",
        "question_type": "open",
        "grade": [
          6
        ],
        "source": "Мединский, История России, 6 кл.",
        "themes": [
          "Русские земли и Золотая Орда"
        ]
      }
    },
    {
      "id": "g6-rus-s26-27-018",
      "type": "open",
      "question": "Кратко объясните значение понятия или события «Православная церковь».",
      "correct_answer": "сохранила важное положение и способствовала духовному единству Руси",
      "acceptable_answers": [
        "сохранила важное положение и способствовала духовному единству Руси",
        "Православная церковь: сохранила важное положение и способствовала духовному единству Руси"
      ],
      "explanation": "Ответ должен раскрывать смысл термина в теме «Русские земли и Золотая Орда»: сохранила важное положение и способствовала духовному единству Руси.",
      "source": {
        "paragraph": "§26-27",
        "page": 135
      },
      "difficulty": {
        "primary": "hard",
        "secondary": "medium"
      },
      "tags": {
        "entities": [],
        "concepts": [
          "Русские земли и Золотая Орда",
          "Православная церковь"
        ],
        "processes": [],
        "periods": [
          "XIII—XIV вв."
        ],
        "skills": [
          "explanation"
        ],
        "geography": [
          "Золотая Орда",
          "Сарай",
          "Русские земли"
        ],
        "difficulty": "hard",
        "question_type": "open",
        "grade": [
          6
        ],
        "source": "Мединский, История России, 6 кл.",
        "themes": [
          "Русские земли и Золотая Орда"
        ]
      }
    },
    {
      "id": "g6-rus-s26-27-019",
      "type": "matching",
      "question": "Соотнесите понятия по теме «Русские земли и Золотая Орда» с их значением.",
      "left_items": [
        {
          "id": "L1",
          "text": "Золотая Орда"
        },
        {
          "id": "L2",
          "text": "Сарай"
        },
        {
          "id": "L3",
          "text": "Хан"
        },
        {
          "id": "L4",
          "text": "Ярлык"
        }
      ],
      "right_items": [
        {
          "id": "R1",
          "text": "ханская грамота, дававшая право на княжение"
        },
        {
          "id": "R2",
          "text": "правитель Орды, от которого зависело утверждение русских князей"
        },
        {
          "id": "R3",
          "text": "столица Золотой Орды"
        },
        {
          "id": "R4",
          "text": "государство, возникшее в западной части монгольских владений и подчинившее русские земли"
        }
      ],
      "correct_pairs": [
        {
          "left": "L1",
          "right": "R4"
        },
        {
          "left": "L2",
          "right": "R3"
        },
        {
          "left": "L3",
          "right": "R2"
        },
        {
          "left": "L4",
          "right": "R1"
        }
      ],
      "explanation": "Пары проверяют ключевые понятия раздела «Русские земли и Золотая Орда».",
      "source": {
        "paragraph": "§26-27",
        "page": 135
      },
      "difficulty": {
        "primary": "medium",
        "secondary": "medium"
      },
      "tags": {
        "entities": [],
        "concepts": [
          "Русские земли и Золотая Орда",
          "Золотая Орда",
          "Сарай",
          "Хан",
          "Ярлык"
        ],
        "processes": [],
        "periods": [
          "XIII—XIV вв."
        ],
        "skills": [
          "classification"
        ],
        "geography": [
          "Золотая Орда",
          "Сарай",
          "Русские земли"
        ],
        "difficulty": "medium",
        "question_type": "matching",
        "grade": [
          6
        ],
        "source": "Мединский, История России, 6 кл.",
        "themes": [
          "Русские земли и Золотая Орда"
        ]
      }
    },
    {
      "id": "g6-rus-s26-27-020",
      "type": "chronology",
      "question": "Расположите события по теме «Русские земли и Золотая Орда» в хронологическом порядке.",
      "items": [
        "1240-е гг. — установление зависимости Руси от Орды",
        "1257 г. — перепись населения для сбора дани",
        "XIII в. — поездки русских князей за ярлыками",
        "XIV в. — усиление русских княжеств в условиях ордынской зависимости"
      ],
      "correct_order": [
        0,
        1,
        2,
        3
      ],
      "correct_answers": [
        "1240-е гг. — установление зависимости Руси от Орды",
        "1257 г. — перепись населения для сбора дани",
        "XIII в. — поездки русских князей за ярлыками",
        "XIV в. — усиление русских княжеств в условиях ордынской зависимости"
      ],
      "explanation": "Хронология раздела: 1240-е гг. — установление зависимости Руси от Орды; 1257 г. — перепись населения для сбора дани; XIII в. — поездки русских князей за ярлыками; XIV в. — усиление русских княжеств в условиях ордынской зависимости.",
      "source": {
        "paragraph": "§26-27",
        "page": 135
      },
      "difficulty": {
        "primary": "hard",
        "secondary": "medium"
      },
      "tags": {
        "entities": [],
        "concepts": [
          "Русские земли и Золотая Орда",
          "установление зависимости Руси от Орды",
          "перепись населения для сбора дани",
          "поездки русских князей за ярлыками",
          "усиление русских княжеств в условиях ордынской зависимости"
        ],
        "processes": [],
        "periods": [
          "XIII—XIV вв."
        ],
        "skills": [
          "chronology"
        ],
        "geography": [
          "Золотая Орда",
          "Сарай",
          "Русские земли"
        ],
        "difficulty": "hard",
        "question_type": "chronology",
        "grade": [
          6
        ],
        "source": "Мединский, История России, 6 кл.",
        "themes": [
          "Русские земли и Золотая Орда"
        ]
      }
    }
  ]
}