{
  "meta": {
    "textbook": "История Древнего мира, 5 класс, В. Р. Мединский",
    "section": "Древняя Палестина",
    "note": "Вопросы составлены по учебнику В. Р. Мединского и соавторов для 5 класса (история Древнего мира). Номера страниц ориентировочные."
  },
  "questions": [
    {
      "id": "g2-p14-001",
      "type": "single_choice",
      "question": "Где расположена Палестина?",
      "options": [
        "Между Египтом и Сирией",
        "Между Индией и Китаем",
        "В Нубии",
        "На Британских островах"
      ],
      "correct_answers": [
        "Между Египтом и Сирией"
      ],
      "explanation": "Географическое положение названо во врезке.",
      "source": {
        "paragraph": "",
        "page": 82
      },
      "difficulty": {
        "primary": "medium",
        "secondary": "medium"
      },
      "tags": {
        "entities": [],
        "concepts": [],
        "processes": [],
        "periods": [],
        "skills": [
          "knowledge"
        ],
        "geography": [
          "Палестина",
          "Левант",
          "Восточное Средиземноморье"
        ],
        "difficulty": "medium",
        "question_type": "single_choice",
        "grade": [
          5
        ],
        "source": "Мединский, История Древнего мира, 5 кл.",
        "themes": [
          "Древняя Палестина",
          "Ханаан",
          "Палестина"
        ]
      }
    },
    {
      "id": "g2-p14-002",
      "type": "single_choice",
      "question": "Как называлась основная часть Палестины в древности, где жили ханаанеи?",
      "options": [
        "Нубия",
        "Ханаан",
        "Аккад",
        "Шумер"
      ],
      "correct_answers": [
        "Ханаан"
      ],
      "explanation": "Текст: большая часть Палестины называлась Ханааном.",
      "source": {
        "paragraph": "",
        "page": 82
      },
      "difficulty": {
        "primary": "medium",
        "secondary": "medium"
      },
      "tags": {
        "entities": [
          "Шумер"
        ],
        "concepts": [],
        "processes": [],
        "periods": [],
        "skills": [
          "knowledge"
        ],
        "geography": [
          "Левант",
          "Восточное Средиземноморье"
        ],
        "difficulty": "medium",
        "question_type": "single_choice",
        "grade": [
          5
        ],
        "source": "Мединский, История Древнего мира, 5 кл.",
        "themes": [
          "Древняя Палестина",
          "Ханаан",
          "Палестина",
          "Месопотамия"
        ]
      }
    },
    {
      "id": "g2-p14-003",
      "type": "single_choice",
      "question": "Какой народ был основным населением Ханаана, помимо упоминания финикийцев?",
      "options": [
        "Шумеры",
        "Ханаанеи (семитский народ)",
        "Хетты",
        "Персы"
      ],
      "correct_answers": [
        "Ханаанеи (семитский народ)"
      ],
      "explanation": "Учебник описывает ханаанеев как основное население.",
      "source": {
        "paragraph": "",
        "page": 82
      },
      "difficulty": {
        "primary": "medium",
        "secondary": "medium"
      },
      "tags": {
        "entities": [
          "Шумер",
          "финикийцы"
        ],
        "concepts": [],
        "processes": [
          "торговля",
          "письменность"
        ],
        "periods": [],
        "skills": [
          "knowledge"
        ],
        "geography": [
          "Левант",
          "Восточное Средиземноморье"
        ],
        "difficulty": "medium",
        "question_type": "single_choice",
        "grade": [
          5
        ],
        "source": "Мединский, История Древнего мира, 5 кл.",
        "themes": [
          "Древняя Палестина",
          "Ханаан",
          "Палестина",
          "Месопотамия",
          "Финикия"
        ]
      }
    },
    {
      "id": "g2-p14-004",
      "type": "single_choice",
      "question": "От чьего названия происходит слово «Палестина»?",
      "options": [
        "От фараонов",
        "От филистимлян",
        "От финикийцев",
        "От римлян V века н. э. только"
      ],
      "correct_answers": [
        "От филистимлян"
      ],
      "explanation": "Текст прямо связывает этимологию с филистимлянами.",
      "source": {
        "paragraph": "",
        "page": 82
      },
      "difficulty": {
        "primary": "medium",
        "secondary": "medium"
      },
      "tags": {
        "entities": [
          "филистимляне",
          "фараоны",
          "финикийцы"
        ],
        "concepts": [
          "власть"
        ],
        "processes": [
          "торговля",
          "письменность"
        ],
        "periods": [],
        "skills": [
          "knowledge"
        ],
        "geography": [
          "Левант",
          "Восточное Средиземноморье",
          "Апеннинский полуостров",
          "Италия",
          "Древний Рим"
        ],
        "difficulty": "medium",
        "question_type": "single_choice",
        "grade": [
          5
        ],
        "source": "Мединский, История Древнего мира, 5 кл.",
        "themes": [
          "Древняя Палестина",
          "Ханаан",
          "Палестина",
          "Финикия"
        ]
      }
    },
    {
      "id": "g2-p14-005",
      "type": "single_choice",
      "question": "В каком веке до н. э. еврейские племена заняли значительную часть Ханаана?",
      "options": [
        "XVI век",
        "XII век",
        "II век",
        "V век н. э."
      ],
      "correct_answers": [
        "XII век"
      ],
      "explanation": "Датировка дана в учебном тексте о заселении Ханаана.",
      "source": {
        "paragraph": "",
        "page": 83
      },
      "difficulty": {
        "primary": "medium",
        "secondary": "medium"
      },
      "tags": {
        "entities": [],
        "concepts": [],
        "processes": [],
        "periods": [],
        "skills": [
          "knowledge"
        ],
        "geography": [
          "Левант",
          "Восточное Средиземноморье"
        ],
        "difficulty": "medium",
        "question_type": "single_choice",
        "grade": [
          5
        ],
        "source": "Мединский, История Древнего мира, 5 кл.",
        "themes": [
          "Древняя Палестина",
          "Ханаан",
          "Палестина"
        ]
      }
    },
    {
      "id": "g2-p14-006",
      "type": "single_choice",
      "question": "К чему со временем перешли древние евреи в религии?",
      "options": [
        "К атеизму",
        "К монотеизму — поклонению одному богу Яхве",
        "Только к культу Ра",
        "Ко многобожию без изменений"
      ],
      "correct_answers": [
        "К монотеизму — поклонению одному богу Яхве"
      ],
      "explanation": "Учебник описывает переход к монотеизму.",
      "source": {
        "paragraph": "",
        "page": 83
      },
      "difficulty": {
        "primary": "medium",
        "secondary": "medium"
      },
      "tags": {
        "entities": [],
        "concepts": [
          "монотеизм",
          "Яхве"
        ],
        "processes": [],
        "periods": [],
        "skills": [
          "knowledge"
        ],
        "geography": [
          "Левант",
          "Восточное Средиземноморье"
        ],
        "difficulty": "medium",
        "question_type": "single_choice",
        "grade": [
          5
        ],
        "source": "Мединский, История Древнего мира, 5 кл.",
        "themes": [
          "Древняя Палестина",
          "Ханаан",
          "Палестина"
        ]
      }
    },
    {
      "id": "g2-p14-007",
      "type": "single_choice",
      "question": "В каком памятнике собраны легенды о происхождении евреев согласно?",
      "options": [
        "Законы Хаммурапи",
        "Ветхий завет",
        "Книга мёртвых",
        "Илиада"
      ],
      "correct_answers": [
        "Ветхий завет"
      ],
      "explanation": "Ветхий Завет назван самой древней частью Библии.",
      "source": {
        "paragraph": "",
        "page": 83
      },
      "difficulty": {
        "primary": "medium",
        "secondary": "medium"
      },
      "tags": {
        "entities": [
          "Хаммурапи"
        ],
        "concepts": [
          "Ветхий завет"
        ],
        "processes": [],
        "periods": [],
        "skills": [
          "knowledge"
        ],
        "geography": [
          "Левант",
          "Восточное Средиземноморье"
        ],
        "difficulty": "medium",
        "question_type": "single_choice",
        "grade": [
          5
        ],
        "source": "Мединский, История Древнего мира, 5 кл.",
        "themes": [
          "Древняя Палестина",
          "Ханаан",
          "Палестина",
          "закон"
        ]
      }
    },
    {
      "id": "g2-p14-008",
      "type": "single_choice",
      "question": "Кого считают родоначальником евреев в преданиях?",
      "options": [
        "Моисей",
        "Авраам",
        "Соломон",
        "Навуходоносор"
      ],
      "correct_answers": [
        "Авраам"
      ],
      "explanation": "Назван Авраам как родоначальник.",
      "source": {
        "paragraph": "",
        "page": 83
      },
      "difficulty": {
        "primary": "medium",
        "secondary": "medium"
      },
      "tags": {
        "entities": [
          "Авраам",
          "Моисей"
        ],
        "concepts": [],
        "processes": [],
        "periods": [],
        "skills": [
          "knowledge"
        ],
        "geography": [
          "Левант",
          "Восточное Средиземноморье"
        ],
        "difficulty": "medium",
        "question_type": "single_choice",
        "grade": [
          5
        ],
        "source": "Мединский, История Древнего мира, 5 кл.",
        "themes": [
          "Древняя Палестина",
          "Ханаан",
          "Палестина",
          "религия"
        ]
      }
    },
    {
      "id": "g2-p14-009",
      "type": "single_choice",
      "question": "Сколько племён составляли Израильский союз по преданиям?",
      "options": [
        "3",
        "7",
        "12",
        "40"
      ],
      "correct_answers": [
        "12"
      ],
      "explanation": "Упомянуты «12 колен израилевых».",
      "source": {
        "paragraph": "",
        "page": 83
      },
      "difficulty": {
        "primary": "medium",
        "secondary": "medium"
      },
      "tags": {
        "entities": [],
        "concepts": [],
        "processes": [],
        "periods": [],
        "skills": [
          "knowledge"
        ],
        "geography": [
          "Левант",
          "Восточное Средиземноморье"
        ],
        "difficulty": "medium",
        "question_type": "single_choice",
        "grade": [
          5
        ],
        "source": "Мединский, История Древнего мира, 5 кл.",
        "themes": [
          "Древняя Палестина",
          "Ханаан",
          "Палестина"
        ]
      }
    },
    {
      "id": "g2-p14-010",
      "type": "single_choice",
      "question": "Кто был первым избранным царём израильтян согласно (~1020 до н. э.)?",
      "options": [
        "Давид",
        "Саул",
        "Соломон",
        "Нехо"
      ],
      "correct_answers": [
        "Саул"
      ],
      "explanation": "Саул назван первым избранным царём.",
      "source": {
        "paragraph": "",
        "page": 83
      },
      "difficulty": {
        "primary": "medium",
        "secondary": "medium"
      },
      "tags": {
        "entities": [
          "Саул"
        ],
        "concepts": [],
        "processes": [],
        "periods": [],
        "skills": [
          "knowledge"
        ],
        "geography": [
          "Левант",
          "Восточное Средиземноморье"
        ],
        "difficulty": "medium",
        "question_type": "single_choice",
        "grade": [
          5
        ],
        "source": "Мединский, История Древнего мира, 5 кл.",
        "themes": [
          "Древняя Палестина",
          "Ханаан",
          "Палестина"
        ]
      }
    },
    {
      "id": "g2-p14-011",
      "type": "single_choice",
      "question": "Кто из царей создал постоянное войско и разгромил филистимлян, правил в 1010—970 до н. э.?",
      "options": [
        "Саул",
        "Давид",
        "Соломон",
        "Саргон"
      ],
      "correct_answers": [
        "Давид"
      ],
      "explanation": "Характеристика Давида в.",
      "source": {
        "paragraph": "",
        "page": 83
      },
      "difficulty": {
        "primary": "medium",
        "secondary": "medium"
      },
      "tags": {
        "entities": [
          "Давид"
        ],
        "concepts": [],
        "processes": [],
        "periods": [],
        "skills": [
          "knowledge"
        ],
        "geography": [
          "Левант",
          "Восточное Средиземноморье"
        ],
        "difficulty": "medium",
        "question_type": "single_choice",
        "grade": [
          5
        ],
        "source": "Мединский, История Древнего мира, 5 кл.",
        "themes": [
          "Древняя Палестина",
          "Ханаан",
          "Палестина"
        ]
      }
    },
    {
      "id": "g2-p14-012",
      "type": "single_choice",
      "question": "Какой город Давид сделал столицей?",
      "options": [
        "Вавилон",
        "Иерусалим",
        "Тир",
        "Самария"
      ],
      "correct_answers": [
        "Иерусалим"
      ],
      "explanation": "Давид захватил Иерусалим и сделал его столицей.",
      "source": {
        "paragraph": "",
        "page": 83
      },
      "difficulty": {
        "primary": "medium",
        "secondary": "medium"
      },
      "tags": {
        "entities": [
          "Вавилон"
        ],
        "concepts": [],
        "processes": [],
        "periods": [],
        "skills": [
          "knowledge"
        ],
        "geography": [
          "Иерусалим",
          "Левант",
          "Восточное Средиземноморье"
        ],
        "difficulty": "medium",
        "question_type": "single_choice",
        "grade": [
          5
        ],
        "source": "Мединский, История Древнего мира, 5 кл.",
        "themes": [
          "Древняя Палестина",
          "Ханаан",
          "Палестина",
          "Вавилония"
        ]
      }
    },
    {
      "id": "g2-p14-013",
      "type": "multiple_choice",
      "question": "Какие факты о филистимлянах соответствуют? Выберите все верные.",
      "options": [
        "Они были опасными западными соседями еврейских племён.",
        "Умели обрабатывать железо, евреи тогда этого не знали.",
        "От их названия происходит слово «Палестина».",
        "Они сразу были покорены без войн.",
        "Давид никогда с ними не сражался."
      ],
      "correct_answers": [
        "Они были опасными западными соседями еврейских племён.",
        "Умели обрабатывать железо, евреи тогда этого не знали.",
        "От их названия происходит слово «Палестина»."
      ],
      "explanation": "Три верных тезиса в тексте; остальное противоречит описанию войн.",
      "source": {
        "paragraph": "",
        "page": 83
      },
      "difficulty": {
        "primary": "hard",
        "secondary": "medium"
      },
      "tags": {
        "entities": [],
        "concepts": [],
        "processes": [],
        "periods": [],
        "skills": [
          "analysis",
          "knowledge",
          "comparison"
        ],
        "geography": [
          "Левант",
          "Восточное Средиземноморье"
        ],
        "difficulty": "hard",
        "question_type": "multiple_choice",
        "grade": [
          5
        ],
        "source": "Мединский, История Древнего мира, 5 кл.",
        "themes": [
          "Древняя Палестина",
          "Ханаан",
          "Палестина"
        ]
      }
    },
    {
      "id": "g2-p14-014",
      "type": "open",
      "question": "Какие виды деятельности и хозяйства перечислены для Древней Палестины в, несмотря на скромные земледельческие условия?",
      "correct_answer": "Земледелие, скотоводство, ремёсла, торговля.",
      "acceptable_answers": [
        "земледели",
        "скотоводств",
        "ремёсла",
        "торговл"
      ],
      "keywords": [
        "земледел",
        "скот",
        "ремесл",
        "торгов"
      ],
      "explanation": "Абзац о природных условиях перечисляет сферы хозяйства.",
      "source": {
        "paragraph": "",
        "page": 82
      },
      "difficulty": {
        "primary": "medium",
        "secondary": "hard"
      },
      "tags": {
        "entities": [],
        "concepts": [],
        "processes": [],
        "periods": [],
        "skills": [
          "comprehension",
          "knowledge",
          "reasoning"
        ],
        "geography": [
          "Левант",
          "Восточное Средиземноморье"
        ],
        "difficulty": "medium",
        "question_type": "open",
        "grade": [
          5
        ],
        "source": "Мединский, История Древнего мира, 5 кл.",
        "themes": [
          "Древняя Палестина",
          "Ханаан",
          "Палестина"
        ]
      }
    },
    {
      "id": "g2-p14-015",
      "type": "open",
      "question": "Что, по более поздним преданиям, сделал Моисей для евреев в религиозном отношении?",
      "correct_answer": "Познакомил с верой в единого бога Яхве и передал заповеди; вывел из Египта и привёл к Ханаану.",
      "acceptable_answers": [
        "Моисей",
        "Яхве",
        "заповед",
        "Египет",
        "Синай"
      ],
      "keywords": [
        "Моисей",
        "Яхв",
        "заповед",
        "един"
      ],
      "explanation": "Описание роли Моисея в.",
      "source": {
        "paragraph": "",
        "page": 83
      },
      "difficulty": {
        "primary": "medium",
        "secondary": "hard"
      },
      "tags": {
        "entities": [
          "Моисей"
        ],
        "concepts": [],
        "processes": [],
        "periods": [],
        "skills": [
          "comprehension",
          "knowledge",
          "reasoning"
        ],
        "geography": [
          "Левант",
          "Восточное Средиземноморье"
        ],
        "difficulty": "medium",
        "question_type": "open",
        "grade": [
          5
        ],
        "source": "Мединский, История Древнего мира, 5 кл.",
        "themes": [
          "Древняя Палестина",
          "Ханаан",
          "Палестина",
          "религия"
        ]
      }
    },
    {
      "id": "g2-p14-016",
      "type": "matching",
      "question": "Сопоставьте царя и событие его правления.",
      "left_items": [
        {
          "id": "L1",
          "text": "Саул"
        },
        {
          "id": "L2",
          "text": "Давид"
        },
        {
          "id": "L3",
          "text": "Соломон"
        },
        {
          "id": "L4",
          "text": "После Соломона"
        }
      ],
      "right_items": [
        {
          "id": "R1",
          "text": "Первый избранный царь (~1020 до н. э.)"
        },
        {
          "id": "R2",
          "text": "Постоянное войско; поражение филистимлян; столица Иерусалим"
        },
        {
          "id": "R3",
          "text": "Мудрый правитель; храм Яхве в Иерусалиме"
        },
        {
          "id": "R4",
          "text": "Разделение на Иудею и Израиль (930—920-е до н. э.)"
        }
      ],
      "correct_pairs": [
        {
          "left": "L1",
          "right": "R1"
        },
        {
          "left": "L2",
          "right": "R2"
        },
        {
          "left": "L3",
          "right": "R3"
        },
        {
          "left": "L4",
          "right": "R4"
        }
      ],
      "explanation": "Пары следуют из изучаемого материала.",
      "source": {
        "paragraph": "",
        "page": 83
      },
      "difficulty": {
        "primary": "medium",
        "secondary": "hard"
      },
      "tags": {
        "entities": [],
        "concepts": [],
        "processes": [],
        "periods": [],
        "skills": [
          "application",
          "knowledge",
          "association"
        ],
        "geography": [
          "Левант",
          "Восточное Средиземноморье"
        ],
        "difficulty": "medium",
        "question_type": "matching",
        "grade": [
          5
        ],
        "source": "Мединский, История Древнего мира, 5 кл.",
        "themes": [
          "Древняя Палестина",
          "Ханаан",
          "Палестина"
        ]
      }
    },
    {
      "id": "g2-p14-017",
      "type": "chronology",
      "question": "Расположите события по заданию «Работаем с хронологией». Задание: расставить события строго по возрастанию времени (от более раннего к более позднему). Ответ (заполните самостоятельно) Ниже впишите ответ: каждая строка — одно событие в вашем порядке (допустимо коротко, по ключевым словам). 1. ______________________________________________ 2. ______________________________________________ 3. ______________________________________________",
      "items": [
        "Правление царя Давида",
        "Правление царя Соломона",
        "Разделение царства на Иудею и Израиль"
      ],
      "correct_order": [
        0,
        1,
        2
      ],
      "correct_answers": [
        "Правление царя Давида",
        "Правление царя Соломона",
        "Разделение царства на Иудею и Израиль"
      ],
      "explanation": "Порядок указан в упражнении учебника: Давид раньше Соломона, затем раскол.",
      "source": {
        "paragraph": "",
        "page": 85
      },
      "difficulty": {
        "primary": "medium",
        "secondary": "hard"
      },
      "tags": {
        "entities": [],
        "concepts": [],
        "processes": [],
        "periods": [],
        "skills": [
          "analysis",
          "chronology",
          "knowledge"
        ],
        "geography": [
          "Левант",
          "Восточное Средиземноморье"
        ],
        "difficulty": "medium",
        "question_type": "chronology",
        "grade": [
          5
        ],
        "source": "Мединский, История Древнего мира, 5 кл.",
        "themes": [
          "Древняя Палестина",
          "Ханаан",
          "Палестина"
        ]
      }
    },
    {
      "id": "g2-p14-018",
      "type": "single_choice",
      "question": "Когда возник иудаизм как религия нового типа?",
      "options": [
        "В XII веке до н. э. сразу",
        "В VIII—VII веках до н. э. в Иудее",
        "В 539 году до н. э.",
        "В I веке н. э."
      ],
      "correct_answers": [
        "В VIII—VII веках до н. э. в Иудее"
      ],
      "explanation": "Датировка и место приведены в.",
      "source": {
        "paragraph": "",
        "page": 84
      },
      "difficulty": {
        "primary": "medium",
        "secondary": "medium"
      },
      "tags": {
        "entities": [],
        "concepts": [
          "иудаизм"
        ],
        "processes": [],
        "periods": [],
        "skills": [
          "knowledge"
        ],
        "geography": [
          "Левант",
          "Восточное Средиземноморье"
        ],
        "difficulty": "medium",
        "question_type": "single_choice",
        "grade": [
          5
        ],
        "source": "Мединский, История Древнего мира, 5 кл.",
        "themes": [
          "Древняя Палестина",
          "Ханаан",
          "Палестина"
        ]
      }
    },
    {
      "id": "g2-p14-019",
      "type": "single_choice",
      "question": "Какие особенности выделяет учебник у иудаизма?",
      "options": [
        "Только многобожие",
        "Единобожие, вера в бессмертие души, загробную жизнь, избранность народа",
        "Отказ от любых законов",
        "Только культ Мардкука"
      ],
      "correct_answers": [
        "Единобожие, вера в бессмертие души, загробную жизнь, избранность народа"
      ],
      "explanation": "Перечень в.",
      "source": {
        "paragraph": "",
        "page": 84
      },
      "difficulty": {
        "primary": "medium",
        "secondary": "medium"
      },
      "tags": {
        "entities": [],
        "concepts": [],
        "processes": [],
        "periods": [],
        "skills": [
          "knowledge"
        ],
        "geography": [
          "Левант",
          "Восточное Средиземноморье"
        ],
        "difficulty": "medium",
        "question_type": "single_choice",
        "grade": [
          5
        ],
        "source": "Мединский, История Древнего мира, 5 кл.",
        "themes": [
          "Древняя Палестина",
          "Ханаан",
          "Палестина"
        ]
      }
    },
    {
      "id": "g2-p14-020",
      "type": "single_choice",
      "question": "Задание на разбор утверждения. Ученик утверждает, что евреи сразу с XII века до н. э. были монотеистами и не знали многобожия. Верно ли это?",
      "options": [
        "Да, всегда были монотеистами",
        "Нет: от многобожия они со временем перешли к монотеизму",
        "Да, они поклонялись только Ра",
        "Нет, монотеизм возник только в XIX веке н. э."
      ],
      "correct_answers": [
        "Нет: от многобожия они со временем перешли к монотеизму"
      ],
      "explanation": "Учебник пишет о переходе от многобожия к монотеизму.",
      "source": {
        "paragraph": "",
        "page": 83
      },
      "difficulty": {
        "primary": "medium",
        "secondary": "medium"
      },
      "tags": {
        "entities": [],
        "concepts": [],
        "processes": [],
        "periods": [],
        "skills": [
          "application",
          "analysis",
          "knowledge"
        ],
        "geography": [
          "Левант",
          "Восточное Средиземноморье"
        ],
        "difficulty": "medium",
        "question_type": "single_choice",
        "grade": [
          5
        ],
        "source": "Мединский, История Древнего мира, 5 кл.",
        "themes": [
          "Древняя Палестина",
          "Ханаан",
          "Палестина"
        ]
      }
    }
  ]
}