{
  "meta": {
    "textbook": "Мединский В.Р. и др. История Древнего мира. 5 класс",
    "section": "§55 Поздняя империя",
    "note": "Банк вопросов для 5 класса. У каждого вопроса указан источник: страница и параграф."
  },
  "questions": [
    {
      "id": "g5-p55-001",
      "type": "single_choice",
      "question": "Что вызвало появление колонов в III веке?",
      "options": [
        "Нехватка рабов и потребность в новой зависимой рабочей силе",
        "Избыток рабов безработных в городах",
        "Полная отмена поместий Августом",
        "Открытие свободной миграции без ограничений"
      ],
      "correct_answers": [
        "Нехватка рабов и потребность в новой зависимой рабочей силе"
      ],
      "explanation": "Колоны возникают из-за дефицита рабов.",
      "source": {
        "paragraph": "§55",
        "page": 289
      },
      "difficulty": {
        "primary": "easy",
        "secondary": "easy"
      },
      "tags": {
        "entities": [],
        "concepts": [],
        "processes": [],
        "periods": [
          "поздняя Античность"
        ],
        "skills": [
          "knowledge"
        ],
        "geography": [
          "Апеннинский полуостров",
          "Италия",
          "Древний Рим"
        ],
        "difficulty": "easy",
        "question_type": "single_choice",
        "grade": [
          5
        ],
        "source": "Мединский, История Древнего мира, 5 кл.",
        "themes": [
          "колонат",
          "Поздняя империя"
        ]
      }
    },
    {
      "id": "g5-p55-002",
      "type": "single_choice",
      "question": "Чем труд колона отличался от труда раба по «Любопытным деталям»?",
      "options": [
        "Колон был заинтересован в результатах собственного хозяйства и работал продуктивнее",
        "Раб всегда работал менее продуктивно без исключений при любых условиях",
        "Колон не имел никакого хозяйства вообще",
        "Раб и колон были юридически полностью тождественны всегда"
      ],
      "correct_answers": [
        "Колон был заинтересован в результатах собственного хозяйства и работал продуктивнее"
      ],
      "explanation": "Подчёркнута большая производительность колона.",
      "source": {
        "paragraph": "§55",
        "page": 289
      },
      "difficulty": {
        "primary": "easy",
        "secondary": "easy"
      },
      "tags": {
        "entities": [],
        "concepts": [],
        "processes": [],
        "periods": [
          "поздняя Античность"
        ],
        "skills": [
          "knowledge"
        ],
        "geography": [
          "Апеннинский полуостров",
          "Италия",
          "Древний Рим"
        ],
        "difficulty": "easy",
        "question_type": "single_choice",
        "grade": [
          5
        ],
        "source": "Мединский, История Древнего мира, 5 кл.",
        "themes": [
          "экономика",
          "Поздняя империя"
        ]
      }
    },
    {
      "id": "g5-p55-003",
      "type": "single_choice",
      "question": "Каких прав лишили колонов позднеримские законы?",
      "options": [
        "Права на брак, наследство и свободное передвижение",
        "Только права на торговлю маслом",
        "Только право на образование без других ограничений",
        "Никаких ограничений не существовало"
      ],
      "correct_answers": [
        "Права на брак, наследство и свободное передвижение"
      ],
      "explanation": "Перечислены ограничения зависимости колона.",
      "source": {
        "paragraph": "§55",
        "page": 289
      },
      "difficulty": {
        "primary": "easy",
        "secondary": "easy"
      },
      "tags": {
        "entities": [],
        "concepts": [],
        "processes": [],
        "periods": [
          "поздняя Античность"
        ],
        "skills": [
          "knowledge"
        ],
        "geography": [
          "Апеннинский полуостров",
          "Италия",
          "Древний Рим"
        ],
        "difficulty": "easy",
        "question_type": "single_choice",
        "grade": [
          5
        ],
        "source": "Мединский, История Древнего мира, 5 кл.",
        "themes": [
          "колонат",
          "Поздняя империя"
        ]
      }
    },
    {
      "id": "g5-p55-004",
      "type": "single_choice",
      "question": "Как называли богатых землевладельцев с несколькими поместьями и вооружёнными отрядами?",
      "options": [
        "Магнаты",
        "Преторианцы",
        "Вестготы без земель",
        "Стоики"
      ],
      "correct_answers": [
        "Магнаты"
      ],
      "explanation": "Так названы крупные владельцы с частными отрядами.",
      "source": {
        "paragraph": "§55",
        "page": 289
      },
      "difficulty": {
        "primary": "easy",
        "secondary": "easy"
      },
      "tags": {
        "entities": [],
        "concepts": [],
        "processes": [],
        "periods": [
          "поздняя Античность"
        ],
        "skills": [
          "knowledge"
        ],
        "geography": [
          "Апеннинский полуостров",
          "Италия",
          "Древний Рим"
        ],
        "difficulty": "easy",
        "question_type": "single_choice",
        "grade": [
          5
        ],
        "source": "Мединский, История Древнего мира, 5 кл.",
        "themes": [
          "магнаты",
          "Поздняя империя"
        ]
      }
    },
    {
      "id": "g5-p55-005",
      "type": "single_choice",
      "question": "Как называлась форма правления Диоклетиана с почти неограниченной властью императора?",
      "options": [
        "Доминат",
        "Принципат",
        "Триумвират",
        "Республика целиком без изменений"
      ],
      "correct_answers": [
        "Доминат"
      ],
      "explanation": "Форма названа доминатом.",
      "source": {
        "paragraph": "§55",
        "page": 290
      },
      "difficulty": {
        "primary": "easy",
        "secondary": "easy"
      },
      "tags": {
        "entities": [
          "Диоклетиан"
        ],
        "concepts": [
          "доминат",
          "республика"
        ],
        "processes": [],
        "periods": [
          "поздняя Античность"
        ],
        "skills": [
          "knowledge"
        ],
        "geography": [
          "Апеннинский полуостров",
          "Италия",
          "Древний Рим"
        ],
        "difficulty": "easy",
        "question_type": "single_choice",
        "grade": [
          5
        ],
        "source": "Мединский, История Древнего мира, 5 кл.",
        "themes": [
          "Диоклетиан",
          "Поздняя империя",
          "Республиканский Рим"
        ]
      }
    },
    {
      "id": "g5-p55-006",
      "type": "single_choice",
      "question": "Что делал эдикт Диоклетиана о «твёрдых ценах»?",
      "options": [
        "Устанавливал предельные цены на продовольствие и оплату труда, наказывая за превышение вплоть до смертной казни",
        "Отменял любые налоги навсегда",
        "Разрешал бесплатную раздачу всего золота гражданам",
        "Запрещал торговлю только хлебом без других товаров"
      ],
      "correct_answers": [
        "Устанавливал предельные цены на продовольствие и оплату труда, наказывая за превышение вплоть до смертной казни"
      ],
      "explanation": "Эдикт направлен против спекуляций.",
      "source": {
        "paragraph": "§55",
        "page": 290
      },
      "difficulty": {
        "primary": "easy",
        "secondary": "easy"
      },
      "tags": {
        "entities": [],
        "concepts": [],
        "processes": [],
        "periods": [
          "поздняя Античность"
        ],
        "skills": [
          "knowledge"
        ],
        "geography": [
          "Апеннинский полуостров",
          "Италия",
          "Древний Рим"
        ],
        "difficulty": "easy",
        "question_type": "single_choice",
        "grade": [
          5
        ],
        "source": "Мединский, История Древнего мира, 5 кл.",
        "themes": [
          "Диоклетиан",
          "Поздняя империя"
        ]
      }
    },
    {
      "id": "g5-p55-007",
      "type": "single_choice",
      "question": "Как Диоклетиан организовал управление огромной империей?",
      "options": [
        "Разделил государство сначала на две, затем на четыре части с соправителями",
        "Убрал все провинции без замены",
        "Передал всё управление только вестготам",
        "Отказался от любой переписи населения"
      ],
      "correct_answers": [
        "Разделил государство сначала на две, затем на четыре части с соправителями"
      ],
      "explanation": "Описано деление на части и соправителей.",
      "source": {
        "paragraph": "§55",
        "page": 290
      },
      "difficulty": {
        "primary": "easy",
        "secondary": "easy"
      },
      "tags": {
        "entities": [],
        "concepts": [],
        "processes": [],
        "periods": [
          "поздняя Античность"
        ],
        "skills": [
          "knowledge"
        ],
        "geography": [
          "Апеннинский полуостров",
          "Италия",
          "Древний Рим"
        ],
        "difficulty": "easy",
        "question_type": "single_choice",
        "grade": [
          5
        ],
        "source": "Мединский, История Древнего мира, 5 кл.",
        "themes": [
          "Диоклетиан",
          "Поздняя империя"
        ]
      }
    },
    {
      "id": "g5-p55-008",
      "type": "single_choice",
      "question": "Что даровал миланский эдикт 313 года?",
      "options": [
        "Свободу исповедания христианской и других религий",
        "Запрет христианства навсегда",
        "Обязанность жертвовать языческим богам каждый день",
        "Перенос столицы немедленно в Карфаген без исключений"
      ],
      "correct_answers": [
        "Свободу исповедания христианской и других религий"
      ],
      "explanation": "Эдикт даровал свободу исповедания.",
      "source": {
        "paragraph": "§55",
        "page": 291
      },
      "difficulty": {
        "primary": "easy",
        "secondary": "easy"
      },
      "tags": {
        "entities": [
          "Константин"
        ],
        "concepts": [],
        "processes": [],
        "periods": [
          "поздняя Античность"
        ],
        "skills": [
          "knowledge"
        ],
        "geography": [
          "Апеннинский полуостров",
          "Италия",
          "Древний Рим"
        ],
        "difficulty": "easy",
        "question_type": "single_choice",
        "grade": [
          5
        ],
        "source": "Мединский, История Древнего мира, 5 кл.",
        "themes": [
          "Константин",
          "Поздняя империя"
        ]
      }
    },
    {
      "id": "g5-p55-009",
      "type": "single_choice",
      "question": "Где Константин заложил новый город-столицу Восточной империи?",
      "options": [
        "На берегу Босфора",
        "На Рубиконе",
        "В Помпеях",
        "На Северном полюсе"
      ],
      "correct_answers": [
        "На берегу Босфора"
      ],
      "explanation": "Константинополь основан на Босфоре.",
      "source": {
        "paragraph": "§55",
        "page": 291
      },
      "difficulty": {
        "primary": "easy",
        "secondary": "easy"
      },
      "tags": {
        "entities": [],
        "concepts": [],
        "processes": [],
        "periods": [
          "поздняя Античность"
        ],
        "skills": [
          "knowledge"
        ],
        "geography": [
          "Апеннинский полуостров",
          "Италия",
          "Древний Рим"
        ],
        "difficulty": "easy",
        "question_type": "single_choice",
        "grade": [
          5
        ],
        "source": "Мединский, История Древнего мира, 5 кл.",
        "themes": [
          "Константинополь",
          "Поздняя империя"
        ]
      }
    },
    {
      "id": "g5-p55-010",
      "type": "multiple_choice",
      "question": "Что из перечисленного относится к гонениям Диоклетиана на христиан?",
      "options": [
        "Эдикты требовали публичного отречения и жертв императору и языческим богам",
        "Отказавших преследовали и подвергали пыткам",
        "Церковь считалась угрозой власти из-за силы организации епископов",
        "Диоклетиан немедленно сделал христианство государственной религией без этапов",
        "Христианам разрешили не платить налоги при отказе от веры"
      ],
      "correct_answers": [
        "Эдикты требовали публичного отречения и жертв императору и языческим богам",
        "Отказавших преследовали и подвергали пыткам",
        "Церковь считалась угрозой власти из-за силы организации епископов"
      ],
      "explanation": "Факты из раздела о Диоклетиане и церкви.",
      "source": {
        "paragraph": "§55",
        "page": 290
      },
      "difficulty": {
        "primary": "medium",
        "secondary": "medium"
      },
      "tags": {
        "entities": [],
        "concepts": [],
        "processes": [],
        "periods": [
          "поздняя Античность"
        ],
        "skills": [
          "knowledge",
          "comparison"
        ],
        "geography": [
          "Апеннинский полуостров",
          "Италия",
          "Древний Рим"
        ],
        "difficulty": "medium",
        "question_type": "multiple_choice",
        "grade": [
          5
        ],
        "source": "Мединский, История Древнего мира, 5 кл.",
        "themes": [
          "гонения",
          "Поздняя империя"
        ]
      }
    },
    {
      "id": "g5-p55-011",
      "type": "multiple_choice",
      "question": "Какие привилегии получила церковь при Константине?",
      "options": [
        "Освобождение от налогов",
        "Право владеть землёй и имуществом",
        "Возможность обогащения церкви как собственника",
        "Полный запрет любых христианских собраний"
      ],
      "correct_answers": [
        "Освобождение от налогов",
        "Право владеть землёй и имуществом",
        "Возможность обогащения церкви как собственника"
      ],
      "explanation": "Перечислено в разделе о Константине.",
      "source": {
        "paragraph": "§55",
        "page": 291
      },
      "difficulty": {
        "primary": "medium",
        "secondary": "medium"
      },
      "tags": {
        "entities": [],
        "concepts": [],
        "processes": [],
        "periods": [
          "поздняя Античность"
        ],
        "skills": [
          "knowledge",
          "comparison"
        ],
        "geography": [
          "Апеннинский полуостров",
          "Италия",
          "Древний Рим"
        ],
        "difficulty": "medium",
        "question_type": "multiple_choice",
        "grade": [
          5
        ],
        "source": "Мединский, История Древнего мира, 5 кл.",
        "themes": [
          "христианство",
          "Поздняя империя"
        ]
      }
    },
    {
      "id": "g5-p55-012",
      "type": "open",
      "question": "Чем принципат Октавиана принципиально отличался от домината Диоклетиана?",
      "correct_answer": "При принципате сохранялись республиканские институты при фактической концентрации власти у принцепса; доминат означал открытую монархическую власть императора с ритуалами поклонения и ослаблением самостоятельности сената.",
      "acceptable_answers": [
        "республиканский фасад",
        "монархия"
      ],
      "keywords": [
        "принципат",
        "доминат"
      ],
      "explanation": "Отличие следует из определений эпох.",
      "source": {
        "paragraph": "§55",
        "page": 289
      },
      "difficulty": {
        "primary": "hard",
        "secondary": "medium"
      },
      "tags": {
        "entities": [],
        "concepts": [],
        "processes": [],
        "periods": [
          "поздняя Античность"
        ],
        "skills": [
          "knowledge",
          "reasoning"
        ],
        "geography": [
          "Апеннинский полуостров",
          "Италия",
          "Древний Рим"
        ],
        "difficulty": "hard",
        "question_type": "open",
        "grade": [
          5
        ],
        "source": "Мединский, История Древнего мира, 5 кл.",
        "themes": [
          "политика",
          "Поздняя империя"
        ]
      }
    },
    {
      "id": "g5-p55-013",
      "type": "open",
      "question": "Почему слово «вандализм» стало означать разрушение культурных ценностей?",
      "correct_answer": "В 455 году вандалы вторглись в Италию и жестоко разграбили Рим, уничтожая памятники; с тех пор такое разрушение стало называть вандализмом.",
      "acceptable_answers": [
        "455 год",
        "вандалы",
        "разграбление Рима"
      ],
      "keywords": [
        "вандализм",
        "Рим"
      ],
      "explanation": "Этимология дана о нашествии вандалов.",
      "source": {
        "paragraph": "§55",
        "page": 292
      },
      "difficulty": {
        "primary": "medium",
        "secondary": "medium"
      },
      "tags": {
        "entities": [],
        "concepts": [],
        "processes": [],
        "periods": [
          "поздняя Античность"
        ],
        "skills": [
          "knowledge",
          "reasoning"
        ],
        "geography": [
          "Апеннинский полуостров",
          "Италия",
          "Древний Рим"
        ],
        "difficulty": "medium",
        "question_type": "open",
        "grade": [
          5
        ],
        "source": "Мединский, История Древнего мира, 5 кл.",
        "themes": [
          "варвары",
          "Поздняя империя"
        ]
      }
    },
    {
      "id": "g5-p55-014",
      "type": "matching",
      "question": "Сопоставьте вождя и событие Великого переселения народов.",
      "left_items": [
        {
          "id": "L1",
          "text": "Аларих"
        },
        {
          "id": "L2",
          "text": "Аттила"
        },
        {
          "id": "L3",
          "text": "Аэций"
        },
        {
          "id": "L4",
          "text": "Одоакр"
        }
      ],
      "right_items": [
        {
          "id": "R1",
          "text": "Вестготы разграбили Рим в 410 году"
        },
        {
          "id": "R2",
          "text": "Вождь гуннов, разгромленный на Каталаунских полях в 451 году"
        },
        {
          "id": "R3",
          "text": "Римский полководец, победивший Аттилу при Каталаунских полях"
        },
        {
          "id": "R4",
          "text": "Сверг последнего императора Запада Ромула Августа"
        }
      ],
      "correct_pairs": [
        {
          "left": "L1",
          "right": "R1"
        },
        {
          "left": "L2",
          "right": "R2"
        },
        {
          "left": "L3",
          "right": "R3"
        },
        {
          "left": "L4",
          "right": "R4"
        }
      ],
      "explanation": "Соответствия основаны на разделе о вторжениях.",
      "source": {
        "paragraph": "§55",
        "page": 292
      },
      "difficulty": {
        "primary": "medium",
        "secondary": "hard"
      },
      "tags": {
        "entities": [],
        "concepts": [],
        "processes": [],
        "periods": [
          "поздняя Античность"
        ],
        "skills": [
          "сопоставление",
          "knowledge",
          "association"
        ],
        "geography": [
          "Апеннинский полуостров",
          "Италия",
          "Древний Рим"
        ],
        "difficulty": "medium",
        "question_type": "matching",
        "grade": [
          5
        ],
        "source": "Мединский, История Древнего мира, 5 кл.",
        "themes": [
          "варвары",
          "Поздняя империя"
        ]
      }
    },
    {
      "id": "g5-p55-015",
      "type": "chronology",
      "question": "Упорядочите ключевые события без календарных дат в формулировках поздней империи из ленты времени.",
      "items": [
        "Миланский эдикт Константина",
        "Разделение империи на Западную и Восточную",
        "Разграбление Рима вестготами",
        "Битва на Каталаунских полях",
        "Разорение Рима вандалами",
        "Падение Западной Римской империи"
      ],
      "correct_order": [
        0,
        1,
        2,
        3,
        4,
        5
      ],
      "correct_answers": [
        "Миланский эдикт Константина",
        "Разделение империи на Западную и Восточную",
        "Разграбление Рима вестготами",
        "Битва на Каталаунских полях",
        "Разорение Рима вандалами",
        "Падение Западной Римской империи"
      ],
      "explanation": "Порядок соответствует ленте времени учебника.",
      "source": {
        "paragraph": "§55",
        "page": 292
      },
      "difficulty": {
        "primary": "medium",
        "secondary": "medium"
      },
      "tags": {
        "entities": [],
        "concepts": [],
        "processes": [],
        "periods": [
          "поздняя Античность"
        ],
        "skills": [
          "хронология",
          "chronology",
          "knowledge"
        ],
        "geography": [
          "Апеннинский полуостров",
          "Италия",
          "Древний Рим"
        ],
        "difficulty": "medium",
        "question_type": "chronology",
        "grade": [
          5
        ],
        "source": "Мединский, История Древнего мира, 5 кл.",
        "themes": [
          "хронология",
          "Поздняя империя"
        ]
      }
    },
    {
      "id": "g5-p55-016",
      "type": "chronology",
      "question": "Расположите административные меры Диоклетиана.",
      "items": [
        "Перепись населения для налогов и прикрепление к месту жительства",
        "Ответственность землевладельцев за сбор налогов с колонов",
        "Обязанность землевладельцев поставлять колонов в армию",
        "Набор варваров в войско для усиления границ"
      ],
      "correct_order": [
        0,
        1,
        2,
        3
      ],
      "correct_answers": [
        "Перепись населения для налогов и прикрепление к месту жительства",
        "Ответственность землевладельцев за сбор налогов с колонов",
        "Обязанность землевладельцев поставлять колонов в армию",
        "Набор варваров в войско для усиления границ"
      ],
      "explanation": "Логика абзацев о налогах и армии при Диоклетиане.",
      "source": {
        "paragraph": "§55",
        "page": 290
      },
      "difficulty": {
        "primary": "medium",
        "secondary": "hard"
      },
      "tags": {
        "entities": [],
        "concepts": [],
        "processes": [],
        "periods": [
          "поздняя Античность"
        ],
        "skills": [
          "chronology",
          "knowledge"
        ],
        "geography": [
          "Апеннинский полуостров",
          "Италия",
          "Древний Рим"
        ],
        "difficulty": "medium",
        "question_type": "chronology",
        "grade": [
          5
        ],
        "source": "Мединский, История Древнего мира, 5 кл.",
        "themes": [
          "Диоклетиан",
          "Поздняя империя"
        ]
      }
    },
    {
      "id": "g5-p55-017",
      "type": "single_choice",
      "question": "Кто возглавлял гуннов, наводивших ужас на римские земли?",
      "options": [
        "Аттила",
        "Аларих",
        "Спартак",
        "Верцингеторикс"
      ],
      "correct_answers": [
        "Аттила"
      ],
      "explanation": "Вождём гуннов назван Аттила.",
      "source": {
        "paragraph": "§55",
        "page": 292
      },
      "difficulty": {
        "primary": "easy",
        "secondary": "easy"
      },
      "tags": {
        "entities": [
          "Аттила"
        ],
        "concepts": [],
        "processes": [],
        "periods": [
          "поздняя Античность"
        ],
        "skills": [
          "knowledge"
        ],
        "geography": [
          "Апеннинский полуостров",
          "Италия",
          "Древний Рим",
          "Эллада",
          "Древняя Греция",
          "Эгейское море"
        ],
        "difficulty": "easy",
        "question_type": "single_choice",
        "grade": [
          5
        ],
        "source": "Мединский, История Древнего мира, 5 кл.",
        "themes": [
          "гунны",
          "Поздняя империя",
          "Спарта"
        ]
      }
    },
    {
      "id": "g5-p55-018",
      "type": "single_choice",
      "question": "Где вестготы создали первое варварское королевство после разграбления Рима?",
      "options": [
        "На юге Галлии со столицей в Тулузе",
        "В Персидском заливе",
        "На Балканах без столицы",
        "На территории Китая"
      ],
      "correct_answers": [
        "На юге Галлии со столицей в Тулузе"
      ],
      "explanation": "Королевство со столицей в Тулузе.",
      "source": {
        "paragraph": "§55",
        "page": 292
      },
      "difficulty": {
        "primary": "easy",
        "secondary": "easy"
      },
      "tags": {
        "entities": [],
        "concepts": [],
        "processes": [],
        "periods": [
          "поздняя Античность"
        ],
        "skills": [
          "knowledge"
        ],
        "geography": [
          "Апеннинский полуостров",
          "Италия",
          "Древний Рим"
        ],
        "difficulty": "easy",
        "question_type": "single_choice",
        "grade": [
          5
        ],
        "source": "Мединский, История Древнего мира, 5 кл.",
        "themes": [
          "вестготы",
          "Поздняя империя"
        ]
      }
    },
    {
      "id": "g5-p55-019",
      "type": "single_choice",
      "question": "Как звали последнего императора Западной Римской империи по иронии судьбы?",
      "options": [
        "Ромул Август",
        "Октавиан Август",
        "Нерон",
        "Траян"
      ],
      "correct_answers": [
        "Ромул Август"
      ],
      "explanation": "Последний император назван Ромул Август.",
      "source": {
        "paragraph": "§55",
        "page": 292
      },
      "difficulty": {
        "primary": "easy",
        "secondary": "easy"
      },
      "tags": {
        "entities": [],
        "concepts": [],
        "processes": [],
        "periods": [
          "поздняя Античность"
        ],
        "skills": [
          "knowledge"
        ],
        "geography": [
          "Апеннинский полуостров",
          "Италия",
          "Древний Рим"
        ],
        "difficulty": "easy",
        "question_type": "single_choice",
        "grade": [
          5
        ],
        "source": "Мединский, История Древнего мира, 5 кл.",
        "themes": [
          "476 год",
          "Поздняя империя"
        ]
      }
    },
    {
      "id": "g5-p55-020",
      "type": "single_choice",
      "question": "Что символически означает 476 год н. э.?",
      "options": [
        "Конец эпохи Древнего мира и начало Средних веков",
        "Окончание только Византии без Запада",
        "Начало завоевания Галлии Цезарём",
        "Дата основания Константинополя"
      ],
      "correct_answers": [
        "Конец эпохи Древнего мира и начало Средних веков"
      ],
      "explanation": "Средневековья.",
      "source": {
        "paragraph": "§55",
        "page": 292
      },
      "difficulty": {
        "primary": "easy",
        "secondary": "medium"
      },
      "tags": {
        "entities": [],
        "concepts": [],
        "processes": [],
        "periods": [
          "поздняя Античность"
        ],
        "skills": [
          "knowledge"
        ],
        "geography": [
          "Апеннинский полуостров",
          "Италия",
          "Древний Рим"
        ],
        "difficulty": "easy",
        "question_type": "single_choice",
        "grade": [
          5
        ],
        "source": "Мединский, История Древнего мира, 5 кл.",
        "themes": [
          "хронология",
          "Поздняя империя"
        ]
      }
    }
  ]
}
